uproot_custom/AsCustom.py
uproot_custom/__init__.py
uproot_custom/_version.py
uproot_custom/cpp.cpython-311-x86_64-linux-gnu.so
uproot_custom/cpp.pyi
uproot_custom/factories.py
uproot_custom/utils.py
uproot_custom/include/uproot-custom/uproot-custom.hh
uproot_custom/share/cmake/__init__.py
uproot_custom/share/cmake/uproot-customConfig.cmake
uproot_custom/share/cmake/uproot-customConfigVersion.cmake
uproot_custom-2.1.1.dist-info/METADATA
uproot_custom-2.1.1.dist-info/WHEEL
uproot_custom-2.1.1.dist-info/entry_points.txt
uproot_custom-2.1.1.dist-info/RECORD
uproot_custom-2.1.1.dist-info/licenses/LICENSE
